<?xml version="1.0"?>
<page xmlns:xsi="http://www.w3.org/2001/XMLSchema-instance"
      xsi:noNamespaceSchemaLocation="urn:magento:framework:View/Layout/etc/page_configuration.xsd">
    <body>
        <referenceContainer name="after.body.start">
            <block class="Magento\Cookie\Block\Html\Notices" name="cookie_notices"
                   template="Pointeger_Cookie::html/notices.phtml">
                <arguments>
                    <argument name="view_model" xsi:type="object">Pointeger\Cookie\ViewModel\CustomCookie</argument>
                </arguments>
            </block>
        </referenceContainer>
    </body>
</page>
